{
  "text": [
    "Tive meu primeiro contato com programação por volta dos 17 anos quando decidi estudar uma apostila de Java, mas onde me encontrei mesmo foi na área do front-end e não larguei mais. Fiz diversos cursos, e hoje em dia sigo os estudos pelo curso da EBAC e na faculdade, onde curso ciências da computação.",
    "Já desenvolvi diversos projetos, desde landpages para grandes eventos, sites de suporte e pessoais. Sigo interessado em construir diversos sistemas, e caso tenha algum projeto em mente gostaria muito de fazer parte do time!"
  ],
  "curriculum": "https://lipesms.github.io/v2//src/assets/docs/curriculum.pdf",
  "overlay": {
    "years": 24,
    "experienceYears": "+2",
    "projects": "+4"
  }
}
